bingscraper/__init__.py
bingscraper/bingscraper.py
bingscraper-3.0.dist-info/DESCRIPTION.rst
bingscraper-3.0.dist-info/METADATA
bingscraper-3.0.dist-info/RECORD
bingscraper-3.0.dist-info/WHEEL
bingscraper-3.0.dist-info/metadata.json
bingscraper-3.0.dist-info/top_level.txt
